databridges_sio_server_lib/__init__.py
databridges_sio_server_lib/dBridges.py
databridges_sio_server_lib/Tokens/dBToken.py
databridges_sio_server_lib/clientFunctions/clientFunction.py
databridges_sio_server_lib/commonUtils/aioPromise.py
databridges_sio_server_lib/commonUtils/aioTimer.py
databridges_sio_server_lib/commonUtils/util.py
databridges_sio_server_lib/connections/connection.py
databridges_sio_server_lib/dispatchers/dispatcher.py
databridges_sio_server_lib/events/connectChannelEvents.py
databridges_sio_server_lib/events/dBConnectionEvents.py
databridges_sio_server_lib/events/dBEvents.py
databridges_sio_server_lib/exceptions/code.py
databridges_sio_server_lib/exceptions/dBError.py
databridges_sio_server_lib/exceptions/messages.py
databridges_sio_server_lib/exceptions/source.py
databridges_sio_server_lib/messageTypes/dBTypes.py
databridges_sio_server_lib/privateAccess/accessResponse.py
databridges_sio_server_lib/remoteProcedure/rpc.py
databridges_sio_server_lib/remoteProcedure/rpcClient.py
databridges_sio_server_lib/remoteProcedure/rpcServer.py
databridges_sio_server_lib/remoteProcedure/rpcState.py
databridges_sio_server_lib/responseHandler/cfrpcResponse.py
databridges_sio_server_lib/stations/channelState.py
databridges_sio_server_lib/stations/station.py
databridges_sio_server_lib/stations/subscribeChannel.py
databridges_sio_server_lib-2.0.5.dist-info/licenses/LICENSE
databridges_sio_server_lib-2.0.5.dist-info/WHEEL
databridges_sio_server_lib-2.0.5.dist-info/METADATA
databridges_sio_server_lib-2.0.5.dist-info/RECORD
